mdb_models/__init__.py
mdb_models/aggregator.py
mdb_models/authenticatable.py
mdb_models/base.py
mdb_models/db.py
mdb_models/generate_authmodel.py
mdb_models/generate_model.py
mdb_models/session.py
mdb_models/templates/__init__.py
mdb_models/templates/model_template.py
mdb_models/templates/session_model_template.py
mongodb_data_layer/__init__.py
mongodb_data_layer/aggregator.py
mongodb_data_layer/base.py
mongodb_data_layer/db.py
mongodb_data_layer/generate_model.py
mongodb_data_layer/templates/__init__.py
mongodb_data_layer/templates/model_template.py
mdb_models-3.0.1.dist-info/METADATA
mdb_models-3.0.1.dist-info/WHEEL
mdb_models-3.0.1.dist-info/entry_points.txt
mdb_models-3.0.1.dist-info/top_level.txt
mdb_models-3.0.1.dist-info/RECORD
