Metadata-Version: 2.2
Name: mdb-models
Version: 3.0.1
Summary: A data mapper for mongodb (Formerly mongodb_data_layer)
Author: Marjon Godito
Requires-Dist: pymongo
Requires-Dist: python-dotenv
Requires-Dist: bcrypt
Dynamic: author
Dynamic: description
Dynamic: description-content-type
Dynamic: requires-dist
Dynamic: summary
